urwidgets/__init__.py
urwidgets/hyperlink.py
urwidgets/text_embed.py
urwidgets-0.2.1.dist-info/LICENSE
urwidgets-0.2.1.dist-info/METADATA
urwidgets-0.2.1.dist-info/WHEEL
urwidgets-0.2.1.dist-info/top_level.txt
urwidgets-0.2.1.dist-info/RECORD
