Metadata-Version: 2.1
Name: urwidgets
Version: 0.2.1
Summary: A collection of widgets for urwid (https://urwid.org)
Home-page: https://github.com/AnonymouX47/urwidgets
Author: AnonymouX47
Author-email: anonymoux47@gmail.com
License: MIT
Project-URL: Changelog, https://github.com/AnonymouX47/urwidgets/blob/main/CHANGELOG.md
Project-URL: Documentation, https://urwidgets.readthedocs.io/
Project-URL: Source, https://github.com/AnonymouX47/urwidgets
Project-URL: Tracker, https://github.com/AnonymouX47/urwidgets/issues
Keywords: terminal,console,xterm,library,tui,urwid,curses
Classifier: Environment :: Console
Classifier: License :: OSI Approved :: MIT License
Classifier: Intended Audience :: Developers
Classifier: Operating System :: POSIX :: Linux
Classifier: Operating System :: MacOS
Classifier: Operating System :: Android
Classifier: Programming Language :: Python :: 3
Classifier: Programming Language :: Python :: 3.7
Classifier: Programming Language :: Python :: 3.8
Classifier: Programming Language :: Python :: 3.9
Classifier: Programming Language :: Python :: 3.10
Classifier: Programming Language :: Python :: 3.11
Classifier: Programming Language :: Python :: 3.12
Classifier: Programming Language :: Python :: 3 :: Only
Classifier: Topic :: Software Development :: Libraries
Requires-Python: >=3.7
License-File: LICENSE
Requires-Dist: urwid<3.0,>=2.1
